tinydb_sqlite/__init__.py
tinydb_sqlite/storages.py
tinydb_sqlite/utils.py
tinydb_sqlite-0.1.2.dist-info/LICENSE
tinydb_sqlite-0.1.2.dist-info/METADATA
tinydb_sqlite-0.1.2.dist-info/WHEEL
tinydb_sqlite-0.1.2.dist-info/RECORD
