Metadata-Version: 2.1
Name: tinydb-sqlite
Version: 0.1.2
Summary: 
Home-page: https://github.com/Cologler/tinydb_sqlite-python
License: MIT
Author: Cologler
Author-email: skyoflw@gmail.com
Requires-Python: >=3.8,<4.0
Classifier: License :: OSI Approved :: MIT License
Classifier: Programming Language :: Python :: 3
Classifier: Programming Language :: Python :: 3.8
Classifier: Programming Language :: Python :: 3.9
Classifier: Programming Language :: Python :: 3.10
Classifier: Programming Language :: Python :: 3.11
Requires-Dist: tinydb (>=4.1.1,<5.0.0)
